setup.py
bin/mdiblasioquickp
mdiblasioquickp/__init__.py
mdiblasioquickp.egg-info/PKG-INFO
mdiblasioquickp.egg-info/SOURCES.txt
mdiblasioquickp.egg-info/dependency_links.txt
mdiblasioquickp.egg-info/not-zip-safe
mdiblasioquickp.egg-info/top_level.txt