Metadata-Version: 1.0
Name: mdiblasioquickp
Version: 1.0
Summary: Test quickpackage
Home-page: https://github.com/mdiblasio/quickp
Author: mdiblasio
Author-email: mdiblasio72@gmail.com
License: MIT
Platform: UNKNOWN
